pyelectroluxocp/__init__.py
pyelectroluxocp/apiModels.py
pyelectroluxocp/const.py
pyelectroluxocp/getCapabilitiesTODO.py
pyelectroluxocp/gigyaClient.py
pyelectroluxocp/gigyaModels.py
pyelectroluxocp/oneAppApi.py
pyelectroluxocp/oneAppApiClient.py
pyelectroluxocp/urls.py
pyelectroluxocp/webSocketClient.py
pyelectroluxocp-0.1.3.dist-info/LICENSE
pyelectroluxocp-0.1.3.dist-info/METADATA
pyelectroluxocp-0.1.3.dist-info/WHEEL
pyelectroluxocp-0.1.3.dist-info/RECORD
