Metadata-Version: 2.3
Name: pyelectroluxocp
Version: 0.1.3
Summary: Electrolux OneApp OCP API
License: MIT
Keywords: home,automation,electrolux,aeg,ocp,oneapp,api
Author: Woyken
Maintainer: Woyken
Requires-Python: >=3.10,<4.0
Classifier: Development Status :: 3 - Alpha
Classifier: Intended Audience :: Developers
Classifier: License :: OSI Approved :: MIT License
Classifier: Operating System :: OS Independent
Classifier: Programming Language :: Python :: 3
Classifier: Programming Language :: Python :: 3.10
Classifier: Programming Language :: Python :: 3.11
Classifier: Programming Language :: Python :: 3.12
Classifier: Programming Language :: Python :: 3.13
Classifier: Topic :: Home Automation
Classifier: Topic :: Software Development :: Libraries :: Python Modules
Requires-Dist: aiohttp (>=3.9.3,<4.0.0)
Requires-Dist: aiohttp-retry (>=2.8.3,<3.0.0)
Project-URL: Bug Tracker, https://github.com/Woyken/py-electrolux-ocp/issues
Project-URL: Changelog, https://github.com/Woyken/py-electrolux-ocp/releases/
Project-URL: Documentation, https://github.com/Woyken/py-electrolux-ocp/blob/main/README.md
Project-URL: Homepage, https://github.com/Woyken/py-electrolux-ocp/
Project-URL: Repository, https://github.com/Woyken/py-electrolux-ocp.git
